nesc/__init__.py
nesc/service.py
nescs-0.3.5.dist-info/METADATA
nescs-0.3.5.dist-info/WHEEL
nescs-0.3.5.dist-info/top_level.txt
nescs-0.3.5.dist-info/RECORD
