Metadata-Version: 2.1
Name: nescs
Version: 0.3.5
Summary: Библиотека создания моделей вложенных сериализаторов
Home-page: https://github.com/twoics/nesc
Author: cifra-k
License: MIT
Requires-Python: >=3.8
Requires-Dist: Django (>=4.1.9)
Requires-Dist: djangorestframework (>=3.13.1)
